flake8_super/__init__.py
flake8_super/plugin.py
flake8_super-0.1.3.dist-info/LICENSE
flake8_super-0.1.3.dist-info/METADATA
flake8_super-0.1.3.dist-info/WHEEL
flake8_super-0.1.3.dist-info/entry_points.txt
flake8_super-0.1.3.dist-info/top_level.txt
flake8_super-0.1.3.dist-info/RECORD
