Metadata-Version: 2.1
Name: flake8-super
Version: 0.1.3
Summary: Python 3 super() check for flake8
Home-page: https://github.com/meanmail/flake8-super
Author: meanmail
Author-email: example@example.com
License: MIT
Platform: UNKNOWN
Classifier: Framework :: Flake8
Classifier: Environment :: Console
Classifier: Intended Audience :: Developers
Classifier: License :: OSI Approved :: MIT License
Classifier: Programming Language :: Python
Classifier: Programming Language :: Python :: 3
Classifier: Topic :: Software Development :: Libraries :: Python Modules
Classifier: Topic :: Software Development :: Quality Assurance
License-File: LICENSE
Requires-Dist: flake8 (>3.0.0)
Requires-Dist: flake8-plugin-utils (~=1.3.2)
